gcp_process_credentials/__init__.py
gcp_process_credentials/credentials.py
gcp_process_credentials-0.0.2.dist-info/LICENSE
gcp_process_credentials-0.0.2.dist-info/METADATA
gcp_process_credentials-0.0.2.dist-info/WHEEL
gcp_process_credentials-0.0.2.dist-info/top_level.txt
gcp_process_credentials-0.0.2.dist-info/RECORD
