Metadata-Version: 2.1
Name: gcp-process-credentials
Version: 0.0.2
Summary: Python ProcessCredentials for Google Cloud Platform
Home-page: https://github.com/salrashid123/gcp_process_credentials_py
Author: Sal Rashid
Author-email: salrashid123@gmail.com
Classifier: License :: OSI Approved :: Apache Software License
Classifier: Operating System :: OS Independent
Classifier: Development Status :: 3 - Alpha
Classifier: Intended Audience :: Developers
Classifier: Programming Language :: Python
Classifier: Programming Language :: Python :: 3.0
Classifier: Topic :: Software Development :: Libraries
Classifier: Topic :: Software Development :: Libraries :: Python Modules
License-File: LICENSE
Requires-Dist: google-auth (>2.6.3)
